{
  "claim": "V2 presentation can scale/filter/present source DM1 graphics, palette, font metrics, and viewport geometry without storing gameplay state in presentation buffers/config.",
  "dm1Originals": [
    {
      "bytes": 363417,
      "name": "GRAPHICS.DAT",
      "path": "/home/trv2/.openclaw/data/firestaff-original-games/DM/_canonical/dm1/GRAPHICS.DAT",
      "sha256": "2c3aa836925c64c09402bafb03c645932bd03c4f003ad9a86542383b078ecf8e"
    },
    {
      "bytes": 33357,
      "name": "DUNGEON.DAT",
      "path": "/home/trv2/.openclaw/data/firestaff-original-games/DM/_canonical/dm1/DUNGEON.DAT",
      "sha256": "d90b6b1c38fd17e41d63682f8afe5ca3341565b5f5ddae5545f0ce78754bdd85"
    },
    {
      "bytes": 12002,
      "name": "TITLE",
      "path": "/home/trv2/.openclaw/data/firestaff-original-games/DM/_canonical/dm1/TITLE",
      "sha256": "adc7f1916eeef343849f23c047977d307495b29793b796a54aa427ba71dd3745"
    }
  ],
  "errors": [],
  "firestaffChecks": {
    "checkedFiles": [
      "include/dm1_v2_viewport_renderer_pc34.h",
      "src/dm1v2/dm1_v2_settings_pc34.c",
      "src/dm1v2/dm1_v2_viewport_renderer_pc34.c",
      "tests/test_dm1_v2_movement_viewport_pc34.c"
    ],
    "presentationStateIsolation": {
      "DM1_V2_ViewportStateForbiddenTokens": [
        "mapX",
        "mapY",
        "direction",
        "rawMapData",
        "DUNGEON",
        "squareFirstThing",
        "thing",
        "champion",
        "party"
      ],
      "V21_ViewportStateForbiddenTokens": [
        "mapX",
        "mapY",
        "direction",
        "rawMapData",
        "DUNGEON",
        "squareFirstThing",
        "thing",
        "champion",
        "party"
      ],
      "forbiddenRendererIncludes": [
        "#include \"dm1_v2_movement_engine_pc34.h\"",
        "#include \"dm1_v2_movement_command_adapter_pc34.h\"",
        "#include \"dm1_v1_game_state_pc34_compat.h\""
      ]
    }
  },
  "redmcsbAnchors": [
    {
      "file": "COORD.C",
      "function": "G3016_s_LayoutData01 + viewport globals",
      "lineRange": "1654-1722",
      "markers": [
        "{ {  9,   0, 320, 200 }",
        "{  9,   0, 224, 136 }",
        "int16_t G2067_i_ViewportScreenX = 0;",
        "int16_t G2068_i_ViewportScreenY = 33;",
        "G2070_ViewportBitmapByteCount = 15232",
        "int16_t G2073_C224_ViewportPixelWidth = 224;",
        "int16_t G2074_C136_ViewportHeight = 136;"
      ],
      "why": "C007 viewport zone and PC34 viewport geometry stay 320x200 screen / 224x136 viewport / screen origin 0,33."
    },
    {
      "file": "DRAWVIEW.C",
      "function": "F0097_DUNGEONVIEW_DrawViewport / VIDRV_09_BlitViewPort",
      "lineRange": "830-857",
      "markers": [
        "F0694_SetMultipleColorsInPalette(C00_LIGHT0);",
        "F0021_MAIN_BlitToScreen(G0296_puc_Bitmap_Viewport, C007_ZONE_VIEWPORT",
        "F0638_GetZone(C007_ZONE_VIEWPORT",
        "VIDRV_09_BlitViewPort"
      ],
      "why": "The source viewport bitmap is blitted through C007_ZONE_VIEWPORT, not through gameplay-state coordinates."
    },
    {
      "file": "DRAWVIEW.C",
      "function": "F2172_",
      "lineRange": "1077-1100,1208-1213",
      "markers": [
        "{ /* Draw viewport to screen memory */",
        "LDA        #68          /* Height 136 pixels */",
        "56 word copy operations = 112 bytes = 224 pixels = viewport width",
        "STA        0x34a0,Y     /* Start of line 33 on screen.",
        "ADC        #224         /* Viewport pixel width */"
      ],
      "why": "Low-level viewport copy hard-pins height 136, width 224, and screen line 33."
    },
    {
      "file": "DRAWVIEW.C",
      "function": "G8151_LIGHT0..G8156_LIGHT5 + G8176_PaletteTable",
      "lineRange": "97-195,408-419",
      "markers": [
        "COLOR_DEF G8151_LIGHT0[17]",
        "COLOR_DEF G8152_LIGHT1[17]",
        "COLOR_DEF G8156_LIGHT5[17]",
        "COLOR_DEF* G8176_PaletteTable",
        "G8151_LIGHT0,           /* 0 */",
        "G8156_LIGHT5,           /* 5 */"
      ],
      "why": "Dungeon-view palette levels are source tables selected by palette index, not generated by V2 state."
    },
    {
      "file": "IMAGE.C",
      "function": "G2061_DungeonViewPaletteIndices / F0694_SetMultipleColorsInPalette",
      "lineRange": "12-14,140-144",
      "markers": [
        "int16_t G2061_DungeonViewPaletteIndices[6] = { 0, 1, 2, 3, 4, 5 };",
        "void F0694_SetMultipleColorsInPalette",
        "VIDRV_08_SetMultipleColorsInPalette"
      ],
      "why": "Source palette selection uses explicit dungeon-view palette indices and video-driver palette calls."
    },
    {
      "file": "TEXT.C",
      "function": "G0357_puc_InterfaceAndScrollsFont / F0040_TEXT_Print",
      "lineRange": "33-35,372-514",
      "markers": [
        "unsigned char* G0357_puc_InterfaceAndScrollsFont;",
        "void F0040_TEXT_Print(",
        "movea.l G0357_puc_InterfaceAndScrollsFont",
        "Address of the character in the font",
        "addq.w  #6,D3"
      ],
      "why": "The interface font is a source bitmap pointer and text printing walks 5-pixel glyph cells with 1-pixel spacing."
    },
    {
      "file": "COORD.C",
      "function": "text/font metrics",
      "lineRange": "1757-1760,1787-1789",
      "markers": [
        "int16_t G2087_C6_TextCharacterWidth = 6;",
        "int16_t G2088_C7_TextLineHeight = 7;",
        "int16_t G2089_C8_InscriptionCharacterWidth = 8;",
        "int16_t G2090_C8_InscriptionLineHeight = 8;",
        "int16_t G2092_MessageAreaWidth = 320;"
      ],
      "why": "PC34 text metrics are explicit source constants: 6x7 normal text, 8x8 inscriptions, 320-wide PC message row."
    }
  ],
  "redmcsbSourceRoot": "/home/trv2/.openclaw/data/firestaff-redmcsb-source/ReDMCSB_WIP20210206/Toolchains/Common/Source",
  "scope": "DM1 V2 Phase 2 graphics pipeline source isolation",
  "status": "passed"
}
