{
  "schema": "pass80_original_frame_classifier.v1",
  "attempt_dir": "verification-screens/pass112-n2-stable-hud-route",
  "capture_count": 6,
  "dimensions_seen": {
    "320x200": 6
  },
  "expected_sequence": [
    "dungeon_gameplay",
    "dungeon_gameplay",
    "dungeon_gameplay",
    "spell_panel",
    "dungeon_gameplay",
    "inventory"
  ],
  "class_counts": {
    "dungeon_gameplay": 2,
    "wall_closeup": 4
  },
  "duplicate_sha256_counts": {
    "ee7741746ea9b30739238e9f0780f57982bd0abe07bf60cea24e9cf92018e89c": 4
  },
  "honesty": "Classifier/audit only. A 320x200 frame is not parity evidence until its semantic class matches the intended route state.",
  "captures": [
    {
      "file": "verification-screens/pass112-n2-stable-hud-route/image0001-raw.png",
      "width": 320,
      "height": 200,
      "bytes": 8017,
      "sha256": "48ed3743ab6ac9de41689af6c1d3169a8fe00863b4552c1ed813e71c98286397",
      "classification": "dungeon_gameplay",
      "reason": "viewport content with mostly dark in-game right column",
      "expected_class": "dungeon_gameplay",
      "expected_match": true,
      "regions": {
        "viewport": {
          "nonblack_ratio": 0.925,
          "color_ratio": 0.0,
          "unique_colors": 6,
          "mean_rgb": [
            146.05,
            146.05,
            146.05
          ],
          "luma_stddev": 57.48
        },
        "right_action": {
          "nonblack_ratio": 0.0138,
          "color_ratio": 0.0,
          "unique_colors": 2,
          "mean_rgb": [
            3.52,
            3.52,
            3.52
          ],
          "luma_stddev": 29.74
        },
        "spell_area": {
          "nonblack_ratio": 0.0,
          "color_ratio": 0.0,
          "unique_colors": 1,
          "mean_rgb": [
            0.0,
            0.0,
            0.0
          ],
          "luma_stddev": 0.0
        },
        "right_column": {
          "nonblack_ratio": 0.0626,
          "color_ratio": 0.0597,
          "unique_colors": 3,
          "mean_rgb": [
            0.72,
            13.8,
            13.8
          ],
          "luma_stddev": 38.64
        },
        "inventory_extent": {
          "nonblack_ratio": 0.7836,
          "color_ratio": 0.0,
          "unique_colors": 6,
          "mean_rgb": [
            108.91,
            108.91,
            108.91
          ],
          "luma_stddev": 68.96
        },
        "title_top": {
          "nonblack_ratio": 0.0,
          "color_ratio": 0.0,
          "unique_colors": 1,
          "mean_rgb": [
            0.0,
            0.0,
            0.0
          ],
          "luma_stddev": 0.0
        }
      }
    },
    {
      "file": "verification-screens/pass112-n2-stable-hud-route/image0002-raw.png",
      "width": 320,
      "height": 200,
      "bytes": 7766,
      "sha256": "47d61e2ae941b826c01d1e0cd5c1bd90730f54aed04ba05c9fabc0750f9424f7",
      "classification": "dungeon_gameplay",
      "reason": "viewport content with mostly dark in-game right column",
      "expected_class": "dungeon_gameplay",
      "expected_match": true,
      "regions": {
        "viewport": {
          "nonblack_ratio": 0.9169,
          "color_ratio": 0.0,
          "unique_colors": 6,
          "mean_rgb": [
            144.48,
            144.48,
            144.48
          ],
          "luma_stddev": 58.13
        },
        "right_action": {
          "nonblack_ratio": 0.0138,
          "color_ratio": 0.0,
          "unique_colors": 2,
          "mean_rgb": [
            3.52,
            3.52,
            3.52
          ],
          "luma_stddev": 29.74
        },
        "spell_area": {
          "nonblack_ratio": 0.0,
          "color_ratio": 0.0,
          "unique_colors": 1,
          "mean_rgb": [
            0.0,
            0.0,
            0.0
          ],
          "luma_stddev": 0.0
        },
        "right_column": {
          "nonblack_ratio": 0.0626,
          "color_ratio": 0.0597,
          "unique_colors": 3,
          "mean_rgb": [
            0.72,
            13.8,
            13.8
          ],
          "luma_stddev": 38.64
        },
        "inventory_extent": {
          "nonblack_ratio": 0.7673,
          "color_ratio": 0.0,
          "unique_colors": 6,
          "mean_rgb": [
            106.12,
            106.12,
            106.12
          ],
          "luma_stddev": 68.02
        },
        "title_top": {
          "nonblack_ratio": 0.0,
          "color_ratio": 0.0,
          "unique_colors": 1,
          "mean_rgb": [
            0.0,
            0.0,
            0.0
          ],
          "luma_stddev": 0.0
        }
      }
    },
    {
      "file": "verification-screens/pass112-n2-stable-hud-route/image0003-raw.png",
      "width": 320,
      "height": 200,
      "bytes": 7577,
      "sha256": "ee7741746ea9b30739238e9f0780f57982bd0abe07bf60cea24e9cf92018e89c",
      "classification": "wall_closeup",
      "reason": "flat low-color viewport fills inventory extent; unsafe for inventory/spell evidence",
      "expected_class": "dungeon_gameplay",
      "expected_match": false,
      "regions": {
        "viewport": {
          "nonblack_ratio": 0.9969,
          "color_ratio": 0.0,
          "unique_colors": 6,
          "mean_rgb": [
            154.65,
            154.65,
            154.65
          ],
          "luma_stddev": 42.0
        },
        "right_action": {
          "nonblack_ratio": 0.0138,
          "color_ratio": 0.0,
          "unique_colors": 2,
          "mean_rgb": [
            3.52,
            3.52,
            3.52
          ],
          "luma_stddev": 29.74
        },
        "spell_area": {
          "nonblack_ratio": 0.0,
          "color_ratio": 0.0,
          "unique_colors": 1,
          "mean_rgb": [
            0.0,
            0.0,
            0.0
          ],
          "luma_stddev": 0.0
        },
        "right_column": {
          "nonblack_ratio": 0.0626,
          "color_ratio": 0.0597,
          "unique_colors": 3,
          "mean_rgb": [
            0.72,
            13.8,
            13.8
          ],
          "luma_stddev": 38.64
        },
        "inventory_extent": {
          "nonblack_ratio": 0.9937,
          "color_ratio": 0.0,
          "unique_colors": 6,
          "mean_rgb": [
            135.31,
            135.31,
            135.31
          ],
          "luma_stddev": 41.58
        },
        "title_top": {
          "nonblack_ratio": 0.0,
          "color_ratio": 0.0,
          "unique_colors": 1,
          "mean_rgb": [
            0.0,
            0.0,
            0.0
          ],
          "luma_stddev": 0.0
        }
      }
    },
    {
      "file": "verification-screens/pass112-n2-stable-hud-route/image0004-raw.png",
      "width": 320,
      "height": 200,
      "bytes": 7577,
      "sha256": "ee7741746ea9b30739238e9f0780f57982bd0abe07bf60cea24e9cf92018e89c",
      "classification": "wall_closeup",
      "reason": "flat low-color viewport fills inventory extent; unsafe for inventory/spell evidence",
      "expected_class": "spell_panel",
      "expected_match": false,
      "regions": {
        "viewport": {
          "nonblack_ratio": 0.9969,
          "color_ratio": 0.0,
          "unique_colors": 6,
          "mean_rgb": [
            154.65,
            154.65,
            154.65
          ],
          "luma_stddev": 42.0
        },
        "right_action": {
          "nonblack_ratio": 0.0138,
          "color_ratio": 0.0,
          "unique_colors": 2,
          "mean_rgb": [
            3.52,
            3.52,
            3.52
          ],
          "luma_stddev": 29.74
        },
        "spell_area": {
          "nonblack_ratio": 0.0,
          "color_ratio": 0.0,
          "unique_colors": 1,
          "mean_rgb": [
            0.0,
            0.0,
            0.0
          ],
          "luma_stddev": 0.0
        },
        "right_column": {
          "nonblack_ratio": 0.0626,
          "color_ratio": 0.0597,
          "unique_colors": 3,
          "mean_rgb": [
            0.72,
            13.8,
            13.8
          ],
          "luma_stddev": 38.64
        },
        "inventory_extent": {
          "nonblack_ratio": 0.9937,
          "color_ratio": 0.0,
          "unique_colors": 6,
          "mean_rgb": [
            135.31,
            135.31,
            135.31
          ],
          "luma_stddev": 41.58
        },
        "title_top": {
          "nonblack_ratio": 0.0,
          "color_ratio": 0.0,
          "unique_colors": 1,
          "mean_rgb": [
            0.0,
            0.0,
            0.0
          ],
          "luma_stddev": 0.0
        }
      }
    },
    {
      "file": "verification-screens/pass112-n2-stable-hud-route/image0005-raw.png",
      "width": 320,
      "height": 200,
      "bytes": 7577,
      "sha256": "ee7741746ea9b30739238e9f0780f57982bd0abe07bf60cea24e9cf92018e89c",
      "classification": "wall_closeup",
      "reason": "flat low-color viewport fills inventory extent; unsafe for inventory/spell evidence",
      "expected_class": "dungeon_gameplay",
      "expected_match": false,
      "regions": {
        "viewport": {
          "nonblack_ratio": 0.9969,
          "color_ratio": 0.0,
          "unique_colors": 6,
          "mean_rgb": [
            154.65,
            154.65,
            154.65
          ],
          "luma_stddev": 42.0
        },
        "right_action": {
          "nonblack_ratio": 0.0138,
          "color_ratio": 0.0,
          "unique_colors": 2,
          "mean_rgb": [
            3.52,
            3.52,
            3.52
          ],
          "luma_stddev": 29.74
        },
        "spell_area": {
          "nonblack_ratio": 0.0,
          "color_ratio": 0.0,
          "unique_colors": 1,
          "mean_rgb": [
            0.0,
            0.0,
            0.0
          ],
          "luma_stddev": 0.0
        },
        "right_column": {
          "nonblack_ratio": 0.0626,
          "color_ratio": 0.0597,
          "unique_colors": 3,
          "mean_rgb": [
            0.72,
            13.8,
            13.8
          ],
          "luma_stddev": 38.64
        },
        "inventory_extent": {
          "nonblack_ratio": 0.9937,
          "color_ratio": 0.0,
          "unique_colors": 6,
          "mean_rgb": [
            135.31,
            135.31,
            135.31
          ],
          "luma_stddev": 41.58
        },
        "title_top": {
          "nonblack_ratio": 0.0,
          "color_ratio": 0.0,
          "unique_colors": 1,
          "mean_rgb": [
            0.0,
            0.0,
            0.0
          ],
          "luma_stddev": 0.0
        }
      }
    },
    {
      "file": "verification-screens/pass112-n2-stable-hud-route/image0006-raw.png",
      "width": 320,
      "height": 200,
      "bytes": 7577,
      "sha256": "ee7741746ea9b30739238e9f0780f57982bd0abe07bf60cea24e9cf92018e89c",
      "classification": "wall_closeup",
      "reason": "flat low-color viewport fills inventory extent; unsafe for inventory/spell evidence",
      "expected_class": "inventory",
      "expected_match": false,
      "regions": {
        "viewport": {
          "nonblack_ratio": 0.9969,
          "color_ratio": 0.0,
          "unique_colors": 6,
          "mean_rgb": [
            154.65,
            154.65,
            154.65
          ],
          "luma_stddev": 42.0
        },
        "right_action": {
          "nonblack_ratio": 0.0138,
          "color_ratio": 0.0,
          "unique_colors": 2,
          "mean_rgb": [
            3.52,
            3.52,
            3.52
          ],
          "luma_stddev": 29.74
        },
        "spell_area": {
          "nonblack_ratio": 0.0,
          "color_ratio": 0.0,
          "unique_colors": 1,
          "mean_rgb": [
            0.0,
            0.0,
            0.0
          ],
          "luma_stddev": 0.0
        },
        "right_column": {
          "nonblack_ratio": 0.0626,
          "color_ratio": 0.0597,
          "unique_colors": 3,
          "mean_rgb": [
            0.72,
            13.8,
            13.8
          ],
          "luma_stddev": 38.64
        },
        "inventory_extent": {
          "nonblack_ratio": 0.9937,
          "color_ratio": 0.0,
          "unique_colors": 6,
          "mean_rgb": [
            135.31,
            135.31,
            135.31
          ],
          "luma_stddev": 41.58
        },
        "title_top": {
          "nonblack_ratio": 0.0,
          "color_ratio": 0.0,
          "unique_colors": 1,
          "mean_rgb": [
            0.0,
            0.0,
            0.0
          ],
          "luma_stddev": 0.0
        }
      }
    }
  ],
  "warnings": [],
  "problems": [
    "image0003-raw.png: classified wall_closeup, expected dungeon_gameplay",
    "image0004-raw.png: classified wall_closeup, expected spell_panel",
    "image0005-raw.png: classified wall_closeup, expected dungeon_gameplay",
    "image0006-raw.png: classified wall_closeup, expected inventory",
    "duplicate raw frames detected: 1 unique sha256 value(s) repeat"
  ],
  "pass": false
}
